{
  "unpublishedPage": {
    "name": "Customer Home Page",
    "slug": "customer-home-page",
    "layouts": [
      {
        "viewMode": false,
        "dsl": {
          "widgetName": "MainContainer",
          "backgroundColor": "none",
          "rightColumn": 1224,
          "snapColumns": 64,
          "detachFromLayout": true,
          "widgetId": "0",
          "topRow": 0,
          "bottomRow": 630,
          "containerStyle": "none",
          "snapRows": 59,
          "parentRowSpace": 1,
          "type": "CANVAS_WIDGET",
          "canExtend": true,
          "version": 87,
          "minHeight": 610,
          "parentColumnSpace": 1,
          "dynamicBindingPathList": [],
          "leftColumn": 0
        },
        "layoutOnLoadActions": [
          [
            {
              "id": "Customer Home Page_GettingAllVendors",
              "name": "GettingAllVendors",
              "confirmBeforeExecute": false,
              "pluginType": "API",
              "jsonPathKeys": [],
              "timeoutInMillisecond": 10000
            }
          ]
        ],
        "layoutOnLoadActionErrors": [],
        "validOnPageLoadActions": true,
        "id": "Customer Home Page",
        "deleted": false,
        "policies": [],
        "userPermissions": []
      }
    ],
    "userPermissions": [],
    "policies": [],
    "isHidden": false
  },
  "deleted": false,
  "gitSyncId": "656d1cbbb36d5f771a61b67a_656e57fad9b99367ba139548"
}